<?xml version="1.0" encoding="UTF-8" standalone="yes"?>
<addoninfo>
  <uuid>A7F661CF-B97A-4d4d-BC46-CD2EAC511E61</uuid>
  <type>scraper</type>
  <title>IMDb-CN(Chinese)</title>
  <library>imdb-cn.xml</library>
  <version>1.0.0</version>
  <platforms>
    <platform>all</platform>
  </platforms>
  <minversion>
    <xbmc>20000</xbmc>
  </minversion>
  <summary>IMDb-CN Chinese Movie Scraper</summary>
  <description>Download Movie information</description>
  <author>TEAMXBMC</author>
  <supportedcontent>
    <content>movies</content>
  </supportedcontent>
</addoninfo>
